mostlyai/mock/__init__.py
mostlyai/mock/core.py
mostlyai/mock/mcp_server.py
mostlyai_mock-0.2.1.dist-info/METADATA
mostlyai_mock-0.2.1.dist-info/WHEEL
mostlyai_mock-0.2.1.dist-info/entry_points.txt
mostlyai_mock-0.2.1.dist-info/licenses/LICENSE
mostlyai_mock-0.2.1.dist-info/RECORD
