Metadata-Version: 2.4
Name: mostlyai-mock
Version: 0.2.1
Summary: Synthetic Mock Data
Project-URL: homepage, https://github.com/mostly-ai/mostlyai-mock
Project-URL: repository, https://github.com/mostly-ai/mostlyai-mock
Project-URL: documentation, https://mostly-ai.github.io/mostlyai-mock/
Author-email: MOSTLY AI <dev@mostly.ai>
License-Expression: Apache-2.0
License-File: LICENSE
Classifier: Development Status :: 4 - Beta
Classifier: Intended Audience :: Developers
Classifier: Intended Audience :: Financial and Insurance Industry
Classifier: Intended Audience :: Healthcare Industry
Classifier: Intended Audience :: Information Technology
Classifier: Intended Audience :: Science/Research
Classifier: Intended Audience :: Telecommunications Industry
Classifier: License :: OSI Approved :: Apache Software License
Classifier: Operating System :: OS Independent
Classifier: Programming Language :: Python :: 3.10
Classifier: Programming Language :: Python :: 3.11
Classifier: Programming Language :: Python :: 3.12
Classifier: Programming Language :: Python :: 3.13
Classifier: Topic :: Software Development :: Libraries
Classifier: Typing :: Typed
Requires-Python: >=3.10
Requires-Dist: litellm>=1.67.0
Requires-Dist: numpy>=1.26.3
Requires-Dist: pandas>=2.0.0
Requires-Dist: pyarrow>=14.0.0
Requires-Dist: pydantic<3.0.0,>=2.0.0
Requires-Dist: tenacity>=9.1.2
Provides-Extra: litellm-proxy
Requires-Dist: litellm[proxy]>=1.67.0; extra == 'litellm-proxy'
Provides-Extra: mcp
Requires-Dist: fastmcp<3.0.0,>=2.0.0; extra == 'mcp'
